<?xml version="1.0" encoding="UTF-8"?>
<!DOCTYPE list SYSTEM "item.dtd">

<list>
    <armor id="70811" name="Red Cat's Eye (Lv. 1)" >
        <set name="crystal_type" value="NONE"/>
        <set name="dropable" value="false"/>
        <set name="icon" value="icon.etc_bm_jewel_pearl_i00"/>
        <set name="sellable" value="false"/>
        <set name="tradeable" value="false"/>
        <set name="type" value="NONE"/>
        <set name="weight" value="5"/>
        <equip>
            <slot id="BROOCH_JEWEL"/>
        </equip>
        <skills>
            <skill id="55705" level="1"/>
        </skills>
    </armor>
    <armor id="70812" name="Red Cat's Eye (Lv. 2)" add_name="Rare">
        <set name="crystal_type" value="NONE"/>
        <set name="dropable" value="false"/>
        <set name="icon" value="icon.etc_bm_jewel_pearl_i00"/>
        <set name="sellable" value="false"/>
        <set name="tradeable" value="false"/>
        <set name="type" value="NONE"/>
        <set name="weight" value="5"/>
        <equip>
            <slot id="BROOCH_JEWEL"/>
        </equip>
        <skills>
            <skill id="55705" level="2"/>
        </skills>
    </armor>
    <armor id="70813" name="Red Cat's Eye (Lv. 3)">
        <set name="crystal_type" value="NONE"/>
        <set name="dropable" value="false"/>
        <set name="icon" value="icon.etc_bm_jewel_pearl_i00"/>
        <set name="sellable" value="false"/>
        <set name="tradeable" value="false"/>
        <set name="type" value="NONE"/>
        <set name="weight" value="5"/>
        <equip>
            <slot id="BROOCH_JEWEL"/>
        </equip>
        <skills>
            <skill id="55705" level="3"/>
        </skills>
    </armor>
    <armor id="70814" name="Red Cat's Eye (Lv. 4)">
        <set name="crystal_type" value="NONE"/>
        <set name="dropable" value="false"/>
        <set name="icon" value="icon.etc_bm_jewel_pearl_i00"/>
        <set name="sellable" value="false"/>
        <set name="tradeable" value="false"/>
        <set name="type" value="NONE"/>
        <set name="weight" value="5"/>
        <equip>
            <slot id="BROOCH_JEWEL"/>
        </equip>
        <skills>
            <skill id="55705" level="4"/>
        </skills>
    </armor>
    <armor id="70815" name="Red Cat's Eye (Lv. 5)">
        <set name="crystal_type" value="NONE"/>
        <set name="dropable" value="false"/>
        <set name="icon" value="icon.etc_bm_jewel_pearl_i00"/>
        <set name="sellable" value="false"/>
        <set name="tradeable" value="false"/>
        <set name="type" value="NONE"/>
        <set name="weight" value="5"/>
        <equip>
            <slot id="BROOCH_JEWEL"/>
        </equip>
        <skills>
            <skill id="55705" level="5"/>
        </skills>
    </armor>
    <armor id="70816" name="Blue Cat's Eye (Lv. 1)" >
        <set name="crystal_type" value="NONE"/>
        <set name="dropable" value="false"/>
        <set name="icon" value="icon.etc_bm_jewel_pearl_i00"/>
        <set name="sellable" value="false"/>
        <set name="tradeable" value="false"/>
        <set name="type" value="NONE"/>
        <set name="weight" value="5"/>
        <equip>
            <slot id="BROOCH_JEWEL"/>
        </equip>
        <skills>
            <skill id="55706" level="1"/>
        </skills>
    </armor>
    <armor id="70817" name="Blue Cat's Eye (Lv. 2)" add_name="Rare">
        <set name="crystal_type" value="NONE"/>
        <set name="dropable" value="false"/>
        <set name="icon" value="icon.etc_bm_jewel_pearl_i00"/>
        <set name="sellable" value="false"/>
        <set name="tradeable" value="false"/>
        <set name="type" value="NONE"/>
        <set name="weight" value="5"/>
        <equip>
            <slot id="BROOCH_JEWEL"/>
        </equip>
        <skills>
            <skill id="55706" level="2"/>
        </skills>
    </armor>
    <armor id="70818" name="Blue Cat's Eye (Lv. 3)">
        <set name="crystal_type" value="NONE"/>
        <set name="dropable" value="false"/>
        <set name="icon" value="icon.etc_bm_jewel_pearl_i00"/>
        <set name="sellable" value="false"/>
        <set name="tradeable" value="false"/>
        <set name="type" value="NONE"/>
        <set name="weight" value="5"/>
        <equip>
            <slot id="BROOCH_JEWEL"/>
        </equip>
        <skills>
            <skill id="55706" level="3"/>
        </skills>
    </armor>
    <armor id="70819" name="Blue Cat's Eye (Lv. 4)">
        <set name="crystal_type" value="NONE"/>
        <set name="dropable" value="false"/>
        <set name="icon" value="icon.etc_bm_jewel_pearl_i00"/>
        <set name="sellable" value="false"/>
        <set name="tradeable" value="false"/>
        <set name="type" value="NONE"/>
        <set name="weight" value="5"/>
        <equip>
            <slot id="BROOCH_JEWEL"/>
        </equip>
        <skills>
            <skill id="55706" level="4"/>
        </skills>
    </armor>
    <armor id="70820" name="Blue Cat's Eye (Lv. 5)">
        <set name="crystal_type" value="NONE"/>
        <set name="dropable" value="false"/>
        <set name="icon" value="icon.etc_bm_jewel_pearl_i00"/>
        <set name="sellable" value="false"/>
        <set name="tradeable" value="false"/>
        <set name="type" value="NONE"/>
        <set name="weight" value="5"/>
        <equip>
            <slot id="BROOCH_JEWEL"/>
        </equip>
        <skills>
            <skill id="55706" level="5"/>
        </skills>
    </armor>
    <armor id="70831" name="Brooch (Lv. 4)">
        <set name="icon" value="icon.etc_bm_brooch_lavianrose_i00"/>
        <set name="type" value="NONE"/>
        <set name="weight" value="10"/>
        <set name="enchantable" value="false"/>
        <equip>
            <slot id="BROOCH"/>
        </equip>
        <skills>
            <skill id="13659" level="1"/>
            <skill id="13661" level="4"/>
        </skills>
    </armor>
    <armor id="70841" name="Jade (Lv. 4)" add_name="30-day">
        <set name="crystal_type" value="NONE"/>
        <set name="dropable" value="false"/>
        <set name="icon" value="icon.etc_talisman_i01"/>
        <set name="durability" value="43200"/>
        <set name="temporal" value="true"/>
        <set name="sellable" value="false"/>
        <set name="tradeable" value="false"/>
        <set name="type" value="NONE"/>
        <set name="weight" value="5"/>
        <equip>
            <slot id="BROOCH_JEWEL"/>
        </equip>
        <skills>
            <skill id="55474" level="4"/>
        </skills>
    </armor>
    <armor id="70842" name="Vital Stone (Lv. 4)" add_name="30-day">
        <set name="crystal_type" value="NONE"/>
        <set name="dropable" value="false"/>
        <set name="icon" value="icon.etc_bm_jewel_pearl_i00"/>
        <set name="durability" value="43200"/>
        <set name="temporal" value="true"/>
        <set name="sellable" value="false"/>
        <set name="tradeable" value="false"/>
        <set name="type" value="NONE"/>
        <set name="weight" value="5"/>
        <equip>
            <slot id="BROOCH_JEWEL"/>
        </equip>
        <skills>
            <skill id="55472" level="4"/>
            <skill id="55473" level="2"/>
        </skills>
    </armor>
    <armor id="70843" name="Garnet (Lv. 4)" add_name="30-day">
        <set name="crystal_type" value="NONE"/>
        <set name="dropable" value="false"/>
        <set name="icon" value="icon.etc_talisman_i01"/>
        <set name="durability" value="43200"/>
        <set name="temporal" value="true"/>
        <set name="sellable" value="false"/>
        <set name="tradeable" value="false"/>
        <set name="type" value="NONE"/>
        <set name="weight" value="5"/>
        <equip>
            <slot id="BROOCH_JEWEL"/>
        </equip>
        <skills>
            <skill id="55485" level="4"/>
        </skills>
    </armor>
</list>